{
    "original": "DAHLGREN, KNUT A, civilingenjör,\n\nGbg, f i Eskilstuna 29/6/04 av fabr\nAron D o Fredrique Lundquist.\nStud:ex 23, KTH 28, ing\nSiemens-Schuc-kertwerke A G Berlin 28, Sv Siemens ab\nMalmö 30, övering sed 58 samt\nprokurist där o ch dess filial Gbg sed 59.\n-Hobby: golf.\n\nGift 36 m Margit Ahlström, dtr t\nskepps-mätn :kontr J M A o Elsa Sjöblom.\n-Barn: Marianne f 43, Per f 45.\n\nDAHLGREN, KURT G A,\nlantbruks-ingenjör, Vänersborg, f i Rogberga,\nJön-kpgs l, 16/1/24 av lantbr Einar D o\nMaria Sjöquist.\n\nStud:ex Jönkpg 43, KTH 49, kurs f\nlantbr :ing :asp KLH 50-51, eo o ord\nlant-br:ing Östergötl l 54, lantbr:ing\nlantbr:-ndn Vänersb sed 58. - Styr:sekr fören\nStat lantbr:ing, styr :led Sällsk f agron\nhydroteknik.\n\nGift 52 m Karin Franzén f 27, dtr t\ndisp Ragnar F o Ingeborg Blomqvist.\n-Barn: Per f 58, Staffan f 60.\n\nDAHLGREN, LEIF E, kapten,\ngymnastikdirektör, Gbg, f i Lund 6/2/06 av\ndir Theodor D o Thyra Warelius.\nStud:ex Malmö 24, fänr A 3 res 26,\nGCI 29, gymn:- o idr:lär Sigtunask\n35-53, Hvitfeldtska hal sed 53, friidr:instr\nÖrgryte IS. - Kapt A 3 res 40. - SM 18\nggr 26-36 (längd- o grenhopp, häcklöpn,\nfemkamp o tiokamp). - Hobbies: sport,\nfiske, antikviteter.\n\nGift 39 m Inga Lilja f 18, dtr t dir\nRobert L o Karin Larsson. - Barn:\nGöran f 40, Tom f 42, Michael f 45.\n\nDALGREN, LENNART A, direktör,\nGbg, f i Gbg 14/4/22 av köpm Karl\nJohan D o Irma Bäckman.\nStud:ex 41, Gbgs HdlI 42, DHG 47,\nrederitjm Wilson &amp; Co Gbg 47, deläg ab\nSko-Bäckmans sed 48, verkst dir där sed\n62. - Deleg försäkr :bol Bore 55-62, v\nordf Gbgs skohandl:fören sed 59,\nstyr:led Gbgs köpm:förb sed 60, styr:led o\nled AU Skofrämj sed 62. - Hobbies:\ntennis, språk.\n\nGift 47 m Siv Svahnberg f 23, dtr t\nGustav S o Rosa Åhström. - Barn: Sten\nf 48, Jan f 51, Bengt f 54, Lars f 63.\n\n",
    "structured": {
        "0": {
            "full_name": "Knut A Dahlgren",
            "location": "Eskilstuna",
            "occupation": "Civilingenjör",
            "birth_details": {
                "date": "29/06/1904",
                "place": "Eskilstuna",
                "parents": "Aron Dahlgren och Fredrique Lundquist",
                "place_coordinates": {
                    "Latitude": 59.37124859999999,
                    "Longitude": 16.5098045
                }
            },
            "education": [
                {
                    "degree": "Stud:ex",
                    "year": "1923",
                    "institution": "KTH",
                    "institution_coordinates": {
                        "Latitude": 59.3498706,
                        "Longitude": 18.0702566
                    }
                }
            ],
            "career": [
                {
                    "position": "Ing",
                    "years": {
                        "start_year": 1958,
                        "end_year": 1959
                    },
                    "organization": "Sv Siemens ab Malmö"
                }
            ],
            "family": {
                "spouse": "Margit Ahlström",
                "marriage_year": "1936",
                "children": [
                    {
                        "name": "Marianne",
                        "birth_year": "1943"
                    },
                    {
                        "name": "Per",
                        "birth_year": "1945"
                    }
                ]
            },
            "hobbies": [
                "Golf"
            ],
            "location_coordinates": {
                "Latitude": 59.37124859999999,
                "Longitude": 16.5098045
            },
            "occupation_hisco_code": 20,
            "occupation_cosine_similarity": 0.837608280698772,
            "occupation_hisco_occupation": "Engineers, Specialisation Unknown",
            "sector_code": 12,
            "sector_description": "Metal goods factory, Mechanical workshop (light industries)"
        },
        "1": {
            "full_name": "Kurt G A Dahlgren",
            "location": "Vänersborg",
            "occupation": "Lantbruksingenjör",
            "birth_details": {
                "date": "16/01/1924",
                "place": "Rogberga, Jönköpings län",
                "parents": "Einar Dahlgren och Maria Sjöquist",
                "place_coordinates": {
                    "Latitude": 57.7342911,
                    "Longitude": 14.2927325
                }
            },
            "education": [
                {
                    "degree": "Stud:ex",
                    "year": "1943",
                    "institution": "KTH",
                    "institution_coordinates": {
                        "Latitude": 59.3498706,
                        "Longitude": 18.0702566
                    }
                }
            ],
            "career": [
                {
                    "position": "Lantbr:ing",
                    "years": {
                        "start_year": 1958,
                        "end_year": null
                    },
                    "organization": "Lantbr:ing lantbr:ndn Vänersb"
                }
            ],
            "family": {
                "spouse": "Karin Franzén",
                "marriage_year": "1952",
                "children": [
                    {
                        "name": "Per",
                        "birth_year": "1958"
                    },
                    {
                        "name": "Staffan",
                        "birth_year": "1960"
                    }
                ]
            },
            "location_coordinates": {
                "Latitude": 58.3797283,
                "Longitude": 12.3248032
            },
            "occupation_hisco_code": 225,
            "occupation_cosine_similarity": 0.7763947948408411,
            "occupation_hisco_occupation": "Farm Supervisors",
            "sector_code": 8,
            "sector_description": "Wood, sawmill and carpentry industry"
        },
        "2": {
            "full_name": "Leif E Dahlgren",
            "location": "Lund",
            "occupation": "Kapten, Gymnastikdirektör",
            "birth_details": {
                "date": "06/02/1906",
                "place": "Lund",
                "parents": "Theodor Dahlgren och Thyra Warelius",
                "place_coordinates": {
                    "Latitude": 55.7046601,
                    "Longitude": 13.1910073
                }
            },
            "education": [
                {
                    "degree": "Stud:ex",
                    "year": "1924",
                    "institution": "Malmö",
                    "institution_coordinates": {
                        "Latitude": 55.604981,
                        "Longitude": 13.003822
                    }
                }
            ],
            "career": [
                {
                    "position": "Kapt",
                    "years": {
                        "start_year": 1940,
                        "end_year": null
                    },
                    "organization": "A 3 res"
                }
            ],
            "family": {
                "spouse": "Inga Lilja",
                "marriage_year": "1939",
                "children": [
                    {
                        "name": "Göran",
                        "birth_year": "1940"
                    },
                    {
                        "name": "Tom",
                        "birth_year": "1942"
                    },
                    {
                        "name": "Michael",
                        "birth_year": "1945"
                    }
                ]
            },
            "hobbies": [
                "Sport",
                "Fiske",
                "Antikviteter"
            ],
            "location_coordinates": {
                "Latitude": 55.7046601,
                "Longitude": 13.1910073
            },
            "occupation_hisco_code": 180,
            "occupation_cosine_similarity": 0.478881538552106,
            "occupation_hisco_occupation": "Athletes, Sportsmen and Related Workers",
            "sector_code": 12,
            "sector_description": "Metal goods factory, Mechanical workshop (light industries)"
        },
        "3": {
            "full_name": "Lennart A Dalgren",
            "location": "Göteborg",
            "occupation": "Direktör",
            "birth_details": {
                "date": "14/04/1922",
                "place": "Göteborg",
                "parents": "Karl Johan Dahlgren och Irma Bäckman",
                "place_coordinates": {
                    "Latitude": 57.70887,
                    "Longitude": 11.97456
                }
            },
            "education": [
                {
                    "degree": "Stud:ex",
                    "year": "1941",
                    "institution": "Gbgs HdlI",
                    "institution_coordinates": {
                        "Latitude": 60.12816100000001,
                        "Longitude": 18.643501
                    }
                }
            ],
            "career": [
                {
                    "position": "Verkst dir",
                    "years": {
                        "start_year": 1962,
                        "end_year": null
                    },
                    "organization": "Sko-Bäckmans"
                }
            ],
            "family": {
                "spouse": "Siv Svahnberg",
                "marriage_year": "1947",
                "children": [
                    {
                        "name": "Sten",
                        "birth_year": "1948"
                    },
                    {
                        "name": "Jan",
                        "birth_year": "1951"
                    },
                    {
                        "name": "Bengt",
                        "birth_year": "1954"
                    },
                    {
                        "name": "Lars",
                        "birth_year": "1963"
                    }
                ]
            },
            "hobbies": [
                "Tennis",
                "Språk"
            ],
            "location_coordinates": {
                "Latitude": 57.70887,
                "Longitude": 11.97456
            },
            "occupation_hisco_code": 211,
            "occupation_cosine_similarity": 0.658902493383097,
            "occupation_hisco_occupation": "General Managers",
            "sector_code": 6,
            "sector_description": "Building contractor, Concrete goods factory"
        }
    }
}